<?xml version="1.0" encoding="utf-8" ?>
<Patch>
	<Operation Class="PatchOperationSequence">
		<success>Always</success>
		<operations>
			<li Class="PatchOperationAdd">
				<success>Always</success>
				<xpath>Defs/StatDef[not(parts)]</xpath>
				<value>
					<parts/>
				</value>
			</li>
			<li Class="PatchOperationAdd">
				<xpath>Defs/StatDef[defName="TradePriceImprovement"]/parts</xpath>
				<value>
					<li Class="Despicable.StatPart_KarmaOffset"/>
				</value>
			</li>
			<li Class="PatchOperationAdd">
				<xpath>Defs/StatDef[defName="ArrestSuccessChance"]/parts</xpath>
				<value>
					<li Class="Despicable.StatPart_KarmaOffset"/>
				</value>
			</li>
			<li Class="PatchOperationAdd">
				<xpath>Defs/StatDef[defName="NegotiationAbility"]/parts</xpath>
				<value>
					<li Class="Despicable.StatPart_KarmaOffset"/>
				</value>
			</li>
			<li Class="PatchOperationAdd">
				<xpath>Defs/StatDef[defName="SocialImpact"]/parts</xpath>
				<value>
					<li Class="Despicable.StatPart_KarmaOffset"/>
				</value>
			</li>
			<li Class="PatchOperationAdd">
				<xpath>Defs/StatDef[defName="TameAnimalChance"]/parts</xpath>
				<value>
					<li Class="Despicable.StatPart_KarmaOffset"/>
				</value>
			</li>
			<li Class="PatchOperationAdd">
				<xpath>Defs/StatDef[defName="TrainAnimalChance"]/parts</xpath>
				<value>
					<li Class="Despicable.StatPart_KarmaOffset"/>
				</value>
			</li>
			<li Class="PatchOperationAdd">
				<xpath>Defs/StatDef[defName="BondAnimalChanceFactor"]/parts</xpath>
				<value>
					<li Class="Despicable.StatPart_KarmaOffset"/>
				</value>
			</li>
			<li Class="PatchOperationAdd">
				<xpath>Defs/StatDef[defName="SuppressionPower"]/parts</xpath>
				<value>
					<li Class="Despicable.StatPart_KarmaOffset"/>
				</value>
			</li>
			<li Class="PatchOperationAdd">
				<xpath>Defs/StatDef[defName="ConversionPower"]/parts</xpath>
				<value>
					<li Class="Despicable.StatPart_KarmaOffset"/>
				</value>
			</li>
			<li Class="PatchOperationAdd">
				<xpath>Defs/StatDef[defName="CertaintyLossFactor"]/parts</xpath>
				<value>
					<li Class="Despicable.StatPart_KarmaOffset"/>
				</value>
			</li>
			<li Class="PatchOperationAdd">
				<xpath>Defs/StatDef[defName="WorkSpeedGlobal"]/parts</xpath>
				<value>
					<li Class="Despicable.StatPart_ThoughtOffset"/>
				</value>
			</li>
		</operations>
	</Operation>
</Patch>
